MANIFEST.in
README.rst
setup.py
cats/__init__.py
cats/__main__.py
cats.egg-info/PKG-INFO
cats.egg-info/SOURCES.txt
cats.egg-info/dependency_links.txt
cats.egg-info/entry_points.txt
cats.egg-info/requires.txt
cats.egg-info/top_level.txt
cats/database/__init__.py
cats/database/asciiworld.json
cats/database/user_xmission_com.json
cats/parsers/__init__.py
cats/parsers/asciiworld.py
cats/parsers/helpers.py
cats/parsers/user_xmission_com.py