Metadata-Version: 1.1
Name: cats
Version: 0.2.0
Summary: More cats to your life!
Home-page: https://github.com/zzzsochi/cats
Author: UNKNOWN
Author-email: UNKNOWN
License: UNKNOWN
Keywords: cats,development
Platform: UNKNOWN
Classifier: License :: OSI Approved :: BSD License
Classifier: Operating System :: POSIX
Classifier: Programming Language :: Python :: 3.3
Classifier: Programming Language :: Python :: 3.4
Classifier: Programming Language :: Python :: 3.5
Classifier: Topic :: Software Development
